pyRazor/__init__.py
pyRazor/lex.py
pyRazor/razorview.py
pyRazor/scopestack.py
pyRazor/sexylexer.py
pyRazor-0.0.2.post1.dist-info/LICENSE
pyRazor-0.0.2.post1.dist-info/METADATA
pyRazor-0.0.2.post1.dist-info/WHEEL
pyRazor-0.0.2.post1.dist-info/top_level.txt
pyRazor-0.0.2.post1.dist-info/RECORD
