Metadata-Version: 2.1
Name: pyRazor
Version: 0.0.2.post1
Summary: A python implementation of the razor engine
Home-page: https://github.com/luscoma/pyRazor
Author: Alex Lusco
Author-email: hoseinyeganloo@gmail.com
License: MIT
Platform: UNKNOWN
Classifier: Programming Language :: Python :: 3
Classifier: License :: OSI Approved :: MIT License
Classifier: Operating System :: OS Independent
Requires-Python: >=3.6
